romanum/__init__.py
romanum/num2roman.py
romanum/roman2num.py
romanum-0.1.data/scripts/n2r
romanum-0.1.data/scripts/r2n
romanum-0.1.dist-info/METADATA
romanum-0.1.dist-info/WHEEL
romanum-0.1.dist-info/top_level.txt
romanum-0.1.dist-info/RECORD
