Metadata-Version: 2.1
Name: romanum
Version: 0.1
Summary: Roman numeral to/from converter scripts
Home-page: https://github.com/Tulitomaatti/romanum
Author: Eetu Lampsijärvi
Author-email: eetu.lampsijarvi@helsinki.fi
License: UNKNOWN
Download-URL: https://github.com/Tulitomaatti/romanum
Platform: UNKNOWN
Classifier: Programming Language :: Python :: 2
Requires-Dist: nose
